retarus/sms/_async.py
retarus/sms/client.py
retarus/sms/model.py
retarus/sms/sync.py
retarus_sms-1.0.1.dist-info/LICENSE
retarus_sms-1.0.1.dist-info/METADATA
retarus_sms-1.0.1.dist-info/WHEEL
retarus_sms-1.0.1.dist-info/top_level.txt
retarus_sms-1.0.1.dist-info/RECORD
