Metadata-Version: 2.1
Name: retarus-sms
Version: 1.0.1
Author-email: Retarus GmbH <Developers@retarus.com>
License: Apache License
Project-URL: repository, https://github.com/retarus/retarus-python-sms
Requires-Python: >=3.8
License-File: LICENSE
Requires-Dist: retarus-common (==0.1.2)
Requires-Dist: pydantic
Requires-Dist: aiohttp
